meteo_hr/__init__.py
meteo_hr/__main__.py
meteo_hr/api.py
meteo_hr/cache.py
meteo_hr/cli.py
meteo_hr/output.py
meteo_hr/parse.py
meteo_hr/places.py
meteo_hr-1.3.0.dist-info/LICENSE
meteo_hr-1.3.0.dist-info/METADATA
meteo_hr-1.3.0.dist-info/WHEEL
meteo_hr-1.3.0.dist-info/entry_points.txt
meteo_hr-1.3.0.dist-info/top_level.txt
meteo_hr-1.3.0.dist-info/RECORD
