Metadata-Version: 2.1
Name: meteo_hr
Version: 1.3.0
Summary: CLI for printing weather forecast from meteo.hr
Author-email: Ivan Habunek <ivan@habunek.com>
License: GNU GENERAL PUBLIC LICENSE
Project-URL: Homepage, https://git.sr.ht/~ihabunek/meteo_hr
Classifier: Programming Language :: Python :: 3
Classifier: License :: OSI Approved :: GNU General Public License v3 (GPLv3)
Classifier: Operating System :: OS Independent
Classifier: Environment :: Console
Requires-Python: >=3.7
License-File: LICENSE
Requires-Dist: beautifulsoup4 <5.0,>=4.0
Requires-Dist: requests <3.0,>=2.0
Requires-Dist: plotext <6.0,>=5.0
Provides-Extra: dev
Requires-Dist: build ; extra == 'dev'
Requires-Dist: pyright ; extra == 'dev'
Requires-Dist: twine ; extra == 'dev'
Requires-Dist: vermin ; extra == 'dev'
